odoo/addons/stock_move_change_source_location/README.rst
odoo/addons/stock_move_change_source_location/__init__.py
odoo/addons/stock_move_change_source_location/__manifest__.py
odoo/addons/stock_move_change_source_location/i18n/stock_move_change_source_location.pot
odoo/addons/stock_move_change_source_location/readme/CONTRIBUTORS.rst
odoo/addons/stock_move_change_source_location/readme/DESCRIPTION.rst
odoo/addons/stock_move_change_source_location/readme/USAGE.rst
odoo/addons/stock_move_change_source_location/static/description/icon.png
odoo/addons/stock_move_change_source_location/static/description/index.html
odoo/addons/stock_move_change_source_location/tests/__init__.py
odoo/addons/stock_move_change_source_location/tests/test_stock_move_change_source_location.py
odoo/addons/stock_move_change_source_location/views/stock_picking_view.xml
odoo/addons/stock_move_change_source_location/wizards/__init__.py
odoo/addons/stock_move_change_source_location/wizards/stock_move_change_source_location_wizard.py
odoo/addons/stock_move_change_source_location/wizards/stock_move_change_source_location_wizard.xml
odoo13_addon_stock_move_change_source_location-13.0.1.0.1.dev3.dist-info/METADATA
odoo13_addon_stock_move_change_source_location-13.0.1.0.1.dev3.dist-info/WHEEL
odoo13_addon_stock_move_change_source_location-13.0.1.0.1.dev3.dist-info/top_level.txt
odoo13_addon_stock_move_change_source_location-13.0.1.0.1.dev3.dist-info/RECORD
